procyonlexer.py
procyonlexer-1.0.dist-info/METADATA
procyonlexer-1.0.dist-info/WHEEL
procyonlexer-1.0.dist-info/entry_points.txt
procyonlexer-1.0.dist-info/top_level.txt
procyonlexer-1.0.dist-info/RECORD
